looseene/__init__.py
looseene-1.0.0.dist-info/METADATA
looseene-1.0.0.dist-info/WHEEL
looseene-1.0.0.dist-info/top_level.txt
looseene-1.0.0.dist-info/RECORD
