Metadata-Version: 2.4
Name: looseene
Version: 1.0.0
Summary: A tiny, persistent, zero-dependency full-text search engine in pure Python.
Author-email: Hammerok <evgeny2900@example.com>
License: MIT
Project-URL: Homepage, https://github.com/Hammer2900/looseene
Project-URL: Bug Tracker, https://github.com/Hammer2900/looseene/issues
Keywords: search,search-engine,full-text,bm25,lucene,embedded
Classifier: Development Status :: 4 - Beta
Classifier: Intended Audience :: Developers
Classifier: License :: OSI Approved :: MIT License
Classifier: Programming Language :: Python :: 3
Classifier: Programming Language :: Python :: 3.8
Classifier: Programming Language :: Python :: 3.9
Classifier: Programming Language :: Python :: 3.10
Classifier: Programming Language :: Python :: 3.11
Classifier: Programming Language :: Python :: 3.12
Classifier: Topic :: Text Processing :: Indexing
Classifier: Topic :: Database :: Database Engines/Servers
Requires-Python: >=3.7
